sedd/__init__.py
sedd/__main__.py
sedd/cli.py
sedd/driver.py
sedd/main.py
sedd/pipscript.py
sedd/utils.py
sedd/config/__init__.py
sedd/config/config.py
sedd/config/defaults.py
sedd/config/typings.py
sedd/data/__init__.py
sedd/data/files_map.py
sedd/data/sites.py
sedd/meta/__init__.py
sedd/meta/notifications.py
sedd/ubo/__init__.py
sedd/ubo/ubo.py
sedd/ubo/utils.py
sedd/watcher/__init__.py
sedd/watcher/handler.py
sedd/watcher/observer.py
sedd/watcher/recovery.py
sedd/watcher/state.py
sedd-2.4.1.dist-info/licenses/LICENSE
sedd-2.4.1.dist-info/METADATA
sedd-2.4.1.dist-info/WHEEL
sedd-2.4.1.dist-info/entry_points.txt
sedd-2.4.1.dist-info/top_level.txt
sedd-2.4.1.dist-info/RECORD
