Metadata-Version: 2.4
Name: sedd
Version: 2.4.1
Summary: Unofficial, community-made tool for downloading the Stack Exchange data dumps
Author-email: LunarWatcher <oliviawolfie@pm.me>
License-Expression: MIT
Project-URL: Homepage, https://github.com/LunarWatcher/se-data-dump-transformer
Project-URL: Documentation, https://github.com/LunarWatcher/se-data-dump-transformer
Project-URL: Repository, https://github.com/LunarWatcher/se-data-dump-transformer.git
Project-URL: Issues, https://github.com/LunarWatcher/se-data-dump-transformer/issues
Project-URL: Changelog, https://github.com/LunarWatcher/se-data-dump-transformer/blob/master/CHANGELOG.md
Keywords: Stack Exchange,data dump,Stack Exchange data dump,downloader,archival,internet archiving,preservation
Classifier: Development Status :: 5 - Production/Stable
Classifier: Environment :: Console
Classifier: Intended Audience :: Developers
Classifier: Topic :: System :: Archiving
Classifier: Topic :: Utilities
Classifier: Programming Language :: Python :: 3
Classifier: Programming Language :: Python :: 3.11
Classifier: Programming Language :: Python :: 3.12
Classifier: Programming Language :: Python :: 3.13
Classifier: Operating System :: POSIX :: Linux
Classifier: Operating System :: MacOS
Classifier: Operating System :: Microsoft :: Windows
Requires-Python: >=3.11
License-File: LICENSE
Requires-Dist: selenium==4.32.0
Requires-Dist: undetected-geckodriver-lw>=2.1.0
Requires-Dist: desktop-notifier==5.0.1
Requires-Dist: watchdog==4.0.2
Requires-Dist: requests
Requires-Dist: loguru>=0.7.3
Dynamic: license-file
